mimitfuelpy/__init__.py
mimitfuelpy/__version__.py
mimitfuelpy/client.py
mimitfuelpy/main.py
mimitfuelpy/api/__init__.py
mimitfuelpy/api/registry.py
mimitfuelpy/api/search.py
mimitfuelpy/models/__init__.py
mimitfuelpy/models/core/__init__.py
mimitfuelpy/models/core/brand.py
mimitfuelpy/models/core/fuel.py
mimitfuelpy/models/core/service_area.py
mimitfuelpy/models/details/__init__.py
mimitfuelpy/models/details/logo.py
mimitfuelpy/models/details/logo_img.py
mimitfuelpy/models/details/opening_hour.py
mimitfuelpy/models/details/service_area_detail.py
mimitfuelpy/models/details/service_area_service.py
mimitfuelpy/models/enums/__init__.py
mimitfuelpy/models/enums/fuel_type.py
mimitfuelpy/models/enums/service_type.py
mimitfuelpy/models/location/__init__.py
mimitfuelpy/models/location/highway.py
mimitfuelpy/models/location/point_map.py
mimitfuelpy/models/location/province.py
mimitfuelpy/models/location/region.py
mimitfuelpy/models/location/town.py
mimitfuelpy/models/search/__init__.py
mimitfuelpy/models/search/response.py
mimitfuelpy/models/search/criteria/__init__.py
mimitfuelpy/models/search/criteria/search_base_criteria.py
mimitfuelpy/models/search/criteria/search_by_brand_criteria.py
mimitfuelpy/models/search/criteria/search_by_zone_criteria.py
mimitfuelpy/utils/__init__.py
mimitfuelpy/utils/exceptions.py
mimitfuelpy/utils/http_client.py
mimitfuelpy-0.2.1.dist-info/licenses/LICENSE
mimitfuelpy-0.2.1.dist-info/METADATA
mimitfuelpy-0.2.1.dist-info/WHEEL
mimitfuelpy-0.2.1.dist-info/top_level.txt
mimitfuelpy-0.2.1.dist-info/RECORD
