Metadata-Version: 2.4
Name: mimitfuelpy
Version: 0.2.1
Summary: Python library for accessing Mimit Fuel Prices API
Author-email: Francesco Petranzan <contact-me@fpetranzan.me>
Maintainer-email: Francesco Petranzan <contact-me@fpetranzan.me>
License: MIT
Project-URL: Homepage, https://github.com/fpetranzan/mimitFuelPy
Project-URL: Bug Tracker, https://github.com/fpetranzan/mimitFuelPy/issues
Project-URL: Documentation, https://fpetranzan.github.io/mimitFuelPy/
Project-URL: Repository, https://github.com/fpetranzan/mimitFuelPy.git
Keywords: fuel,prices,api,mimit,italy
Classifier: Development Status :: 3 - Alpha
Classifier: Intended Audience :: Developers
Classifier: Operating System :: OS Independent
Classifier: Programming Language :: Python :: 3
Classifier: Programming Language :: Python :: 3.7
Classifier: Programming Language :: Python :: 3.8
Classifier: Programming Language :: Python :: 3.9
Classifier: Programming Language :: Python :: 3.10
Classifier: Programming Language :: Python :: 3.11
Classifier: Programming Language :: Python :: 3.12
Classifier: Topic :: Internet :: WWW/HTTP :: Dynamic Content
Classifier: Topic :: Software Development :: Libraries :: Python Modules
Requires-Python: >=3.7
License-File: LICENSE
Requires-Dist: requests>=2.25.0
Provides-Extra: dev
Requires-Dist: black; extra == "dev"
Requires-Dist: isort; extra == "dev"
Requires-Dist: flake8; extra == "dev"
Requires-Dist: mypy; extra == "dev"
Requires-Dist: pytest>=7.0.0; extra == "dev"
Requires-Dist: pytest-cov>=4.0.0; extra == "dev"
Requires-Dist: pytest-mock>=3.10.0; extra == "dev"
Dynamic: license-file
